lab1/collatz.sv
module collatz( input logic         clk,   // Clock
		input logic 	    go,    // Load value from n; start iterating
		input logic  [31:0] n,     // Start value; only read when go = 1
		output logic [31:0] dout,  // Iteration value: true after go = 1
		output logic 	    done); // True when dout reaches 1

   wire [31:0] dout_next;
   assign dout_next = (dout[0] == 1'b0) ? (dout >> 1) : (3 * dout + 1);

   always_ff @(posedge clk) begin
      if (go) begin
         dout <= n;
         done <= (n==1) || (n==0); // Handle n=0 as a special case to avoid infinite loop
      end else if (!done) begin
         dout <= dout_next;
         done <= (dout_next == 1) || (dout_next == 0);
      end
   end

endmodule

lab1/collatz.vcd
$version Generated by VerilatedVcd $end
$date Fri Feb  6 16:40:39 2026
 $end
$timescale   1ns $end

 $scope module TOP $end
  $var wire  1 + clk $end
  $var wire  1 K done $end
  $var wire 32 C dout [31:0] $end
  $var wire  1 3 go $end
  $var wire 32 ; n [31:0] $end
  $scope module collatz $end
   $var wire  1 + clk $end
   $var wire  1 K done $end
   $var wire 32 C dout [31:0] $end
   $var wire 32 # dout_next [31:0] $end
   $var wire  1 3 go $end
   $var wire 32 ; n [31:0] $end
  $upscope $end
 $upscope $end
$enddefinitions $end


#0
b00000000000000000000000000000000 #
0+
03
b00000000000000000000000000000111 ;
b00000000000000000000000000000000 C
0K
#10
1+
#20
0+
13
#30
b00000000000000000000000000010110 #
1+
b00000000000000000000000000000111 C
#40
0+
#50
1+
#60
0+
03
#70
b00000000000000000000000000001011 #
1+
b00000000000000000000000000010110 C
#80
0+
#90
b00000000000000000000000000100010 #
1+
b00000000000000000000000000001011 C
#100
0+
#110
b00000000000000000000000000010001 #
1+
b00000000000000000000000000100010 C
#120
0+
#130
b00000000000000000000000000110100 #
1+
b00000000000000000000000000010001 C
#140
0+
#150
b00000000000000000000000000011010 #
1+
b00000000000000000000000000110100 C
#160
0+
#170
b00000000000000000000000000001101 #
1+
b00000000000000000000000000011010 C
#180
0+
#190
b00000000000000000000000000101000 #
1+
b00000000000000000000000000001101 C
#200
0+
#210
b00000000000000000000000000010100 #
1+
b00000000000000000000000000101000 C
#220
0+
#230
b00000000000000000000000000001010 #
1+
b00000000000000000000000000010100 C
#240
0+
#250
b00000000000000000000000000000101 #
1+
b00000000000000000000000000001010 C
#260
0+
#270
b00000000000000000000000000010000 #
1+
b00000000000000000000000000000101 C
#280
0+
#290
b00000000000000000000000000001000 #
1+
b00000000000000000000000000010000 C
#300
0+
#310
b00000000000000000000000000000100 #
1+
b00000000000000000000000000001000 C
#320
0+
#330
b00000000000000000000000000000010 #
1+
b00000000000000000000000000000100 C
#340
0+
#350
b00000000000000000000000000000001 #
1+
b00000000000000000000000000000010 C
#360
0+
#370
b00000000000000000000000000000100 #
1+
b00000000000000000000000000000001 C
1K
