lab1/collatz.sv
module collatz( input logic         clk,   // Clock
		input logic 	    go,    // Load value from n; start iterating
		input logic  [31:0] n,     // Start value; only read when go = 1
		output logic [31:0] dout,  // Iteration value: true after go = 1
		output logic 	    done); // True when dout reaches 1

   wire [31:0] dout_next;
   assign dout_next = (dout[0] == 1'b0) ? (dout >> 1) : (3 * dout + 1);

   always_ff @(posedge clk) begin
      if (go) begin
         dout <= n;
         done <= (n==1) || (n==0); // Handle n=0 as a special case to avoid infinite loop
      end else if (!done) begin
         dout <= dout_next;
         done <= (dout_next == 1) || (dout_next == 0);
      end
   end

endmodule

lab1/range.sv
module range
   #(parameter
     RAM_WORDS = 16,            // Number of counts to store in RAM
     RAM_ADDR_BITS = 4)         // Number of RAM address bits
   (input logic         clk,    // Clock
    input logic 	go,     // Read start and start testing
    input logic [31:0] 	start,  // Number to start from or count to read
    output logic 	done,   // True once memory is filled
    output logic [15:0] count); // Iteration count once finished

   logic 		cgo;    // "go" for the Collatz iterator
   logic                cdone;  // "done" from the Collatz iterator
   logic [31:0] 	n;      // number to start the Collatz iterator

// verilator lint_off PINCONNECTEMPTY
   
   // Instantiate the Collatz iterator
   collatz c1(.clk(clk),
	      .go(cgo),
	      .n(n),
	      .done(cdone),
	      .dout());

   logic [RAM_ADDR_BITS - 1:0] 	 num;         // The RAM address to write
   logic 			 running = 0; // True during the iterations

   /* Replace this comment and the code below with your solution,
      which should generate running, done, cgo, n, num, we, and din */

   
   // State machine to control the Collatz iteration process
   always_ff @(posedge clk) begin
      if (go && !running) begin
         // Start new iteration sequence
         running <= 1;
         num <= 0;
         din <= 1;
         cgo <= 1;
         n <= start;
         done <= 0;
         we <= 0;
      end else if (running && !(n==0)) begin
         if (cgo) begin
            // First cycle after starting Collatz - deassert cgo
            cgo <= 0;
         end else if (we) begin
            // Just wrote to RAM - prepare for next number
            we <= 0;
            if (num == RAM_ADDR_BITS'(RAM_WORDS - 1)) begin
               // Finished all iterations
               running <= 0;
               done <= 1;
            end else begin
               // Start next number
               num <= num + 1;
               n <= n + 1;
               din <= 1;
               cgo <= 1;
            end
         end else if (cdone) begin
            // Collatz iteration complete - write count to RAM
            we <= 1;
         end else begin
            // Counting iterations while Collatz is running
            din <= din + 1;
         end
      end else if (done) begin
         // One-cycle pulse for done
         done <= 0;
      end
   end
   
   /* Replace this comment and the code above with your solution */

   logic 			 we;                    // Write din to addr
   logic [15:0] 		 din;                   // Data to write
   logic [15:0] 		 mem[RAM_WORDS - 1:0];  // The RAM itself
   logic [RAM_ADDR_BITS - 1:0] 	 addr;                  // Address to read/write

   assign addr = we ? num : start[RAM_ADDR_BITS-1:0];
   
   always_ff @(posedge clk) begin
      if (we) mem[addr] <= din;
      count <= mem[addr];      
   end

endmodule

lab1/range.vcd
$version Generated by VerilatedVcd $end
$date Fri Feb  6 17:25:38 2026
 $end
$timescale   1ns $end

 $scope module TOP $end
  $var wire  1 7" clk $end
  $var wire 16 W" count [15:0] $end
  $var wire  1 O" done $end
  $var wire  1 ?" go $end
  $var wire 32 G" start [31:0] $end
  $scope module range $end
   $var wire 32 g" RAM_ADDR_BITS [31:0] $end
   $var wire 32 _" RAM_WORDS [31:0] $end
   $var wire  4 3 addr [3:0] $end
   $var wire  1 C cdone $end
   $var wire  1 ; cgo $end
   $var wire  1 7" clk $end
   $var wire 16 W" count [15:0] $end
   $var wire 16 c din [15:0] $end
   $var wire  1 O" done $end
   $var wire  1 ?" go $end
   $var wire 16 k mem(0) [15:0] $end
   $var wire 16 l mem(1) [15:0] $end
   $var wire 16 u mem(10) [15:0] $end
   $var wire 16 v mem(11) [15:0] $end
   $var wire 16 w mem(12) [15:0] $end
   $var wire 16 x mem(13) [15:0] $end
   $var wire 16 y mem(14) [15:0] $end
   $var wire 16 z mem(15) [15:0] $end
   $var wire 16 m mem(2) [15:0] $end
   $var wire 16 n mem(3) [15:0] $end
   $var wire 16 o mem(4) [15:0] $end
   $var wire 16 p mem(5) [15:0] $end
   $var wire 16 q mem(6) [15:0] $end
   $var wire 16 r mem(7) [15:0] $end
   $var wire 16 s mem(8) [15:0] $end
   $var wire 16 t mem(9) [15:0] $end
   $var wire 32 K n [31:0] $end
   $var wire  4 S num [3:0] $end
   $var wire  1 # running $end
   $var wire 32 G" start [31:0] $end
   $var wire  1 [ we $end
   $scope module c1 $end
    $var wire  1 7" clk $end
    $var wire  1 C done $end
    $var wire 32 /" dout [31:0] $end
    $var wire 32 + dout_next [31:0] $end
    $var wire  1 ; go $end
    $var wire 32 K n [31:0] $end
   $upscope $end
  $upscope $end
 $upscope $end
$enddefinitions $end


#0
0#
b00000000000000000000000000000000 +
b0111 3
0;
0C
b00000000000000000000000000000000 K
b0000 S
0[
b0000000000000000 c
b0000000000000000 k
b0000000000000000 l
b0000000000000000 m
b0000000000000000 n
b0000000000000000 o
b0000000000000000 p
b0000000000000000 q
b0000000000000000 r
b0000000000000000 s
b0000000000000000 t
b0000000000000000 u
b0000000000000000 v
b0000000000000000 w
b0000000000000000 x
b0000000000000000 y
b0000000000000000 z
b00000000000000000000000000000000 /"
07"
1?"
b00000000000000000000000000000111 G"
0O"
b0000000000000000 W"
b00000000000000000000000000010000 _"
b00000000000000000000000000000100 g"
#10
1#
1;
b00000000000000000000000000000111 K
b0000000000000001 c
17"
#20
07"
#30
b00000000000000000000000000010110 +
0;
b00000000000000000000000000000111 /"
17"
#40
07"
0?"
#50
b00000000000000000000000000001011 +
b0000000000000010 c
b00000000000000000000000000010110 /"
17"
#60
07"
#70
b00000000000000000000000000100010 +
b0000000000000011 c
b00000000000000000000000000001011 /"
17"
#80
07"
#90
b00000000000000000000000000010001 +
b0000000000000100 c
b00000000000000000000000000100010 /"
17"
#100
07"
#110
b00000000000000000000000000110100 +
b0000000000000101 c
b00000000000000000000000000010001 /"
17"
#120
07"
#130
b00000000000000000000000000011010 +
b0000000000000110 c
b00000000000000000000000000110100 /"
17"
#140
07"
#150
b00000000000000000000000000001101 +
b0000000000000111 c
b00000000000000000000000000011010 /"
17"
#160
07"
#170
b00000000000000000000000000101000 +
b0000000000001000 c
b00000000000000000000000000001101 /"
17"
#180
07"
#190
b00000000000000000000000000010100 +
b0000000000001001 c
b00000000000000000000000000101000 /"
17"
#200
07"
#210
b00000000000000000000000000001010 +
b0000000000001010 c
b00000000000000000000000000010100 /"
17"
#220
07"
#230
b00000000000000000000000000000101 +
b0000000000001011 c
b00000000000000000000000000001010 /"
17"
#240
07"
#250
b00000000000000000000000000010000 +
b0000000000001100 c
b00000000000000000000000000000101 /"
17"
#260
07"
#270
b00000000000000000000000000001000 +
b0000000000001101 c
b00000000000000000000000000010000 /"
17"
#280
07"
#290
b00000000000000000000000000000100 +
b0000000000001110 c
b00000000000000000000000000001000 /"
17"
#300
07"
#310
b00000000000000000000000000000010 +
b0000000000001111 c
b00000000000000000000000000000100 /"
17"
#320
07"
#330
b00000000000000000000000000000001 +
b0000000000010000 c
b00000000000000000000000000000010 /"
17"
#340
07"
#350
b00000000000000000000000000000100 +
1C
b0000000000010001 c
b00000000000000000000000000000001 /"
17"
#360
07"
#370
b0000 3
1[
17"
#380
07"
#390
b0111 3
1;
b00000000000000000000000000001000 K
b0001 S
0[
b0000000000000001 c
b0000000000010001 k
17"
#400
07"
#410
0;
0C
b00000000000000000000000000001000 /"
17"
#420
07"
#430
b00000000000000000000000000000010 +
b0000000000000010 c
b00000000000000000000000000000100 /"
17"
#440
07"
#450
b00000000000000000000000000000001 +
b0000000000000011 c
b00000000000000000000000000000010 /"
17"
#460
07"
#470
b00000000000000000000000000000100 +
1C
b0000000000000100 c
b00000000000000000000000000000001 /"
17"
#480
07"
#490
b0001 3
1[
17"
#500
07"
#510
b0111 3
1;
b00000000000000000000000000001001 K
b0010 S
0[
b0000000000000001 c
b0000000000000100 l
17"
#520
07"
#530
b00000000000000000000000000011100 +
0;
0C
b00000000000000000000000000001001 /"
17"
#540
07"
#550
b00000000000000000000000000001110 +
b0000000000000010 c
b00000000000000000000000000011100 /"
17"
#560
07"
#570
b00000000000000000000000000000111 +
b0000000000000011 c
b00000000000000000000000000001110 /"
17"
#580
07"
#590
b00000000000000000000000000010110 +
b0000000000000100 c
b00000000000000000000000000000111 /"
17"
#600
07"
#610
b00000000000000000000000000001011 +
b0000000000000101 c
b00000000000000000000000000010110 /"
17"
#620
07"
#630
b00000000000000000000000000100010 +
b0000000000000110 c
b00000000000000000000000000001011 /"
17"
#640
07"
#650
b00000000000000000000000000010001 +
b0000000000000111 c
b00000000000000000000000000100010 /"
17"
#660
07"
#670
b00000000000000000000000000110100 +
b0000000000001000 c
b00000000000000000000000000010001 /"
17"
#680
07"
#690
b00000000000000000000000000011010 +
b0000000000001001 c
b00000000000000000000000000110100 /"
17"
#700
07"
#710
b00000000000000000000000000001101 +
b0000000000001010 c
b00000000000000000000000000011010 /"
17"
#720
07"
#730
b00000000000000000000000000101000 +
b0000000000001011 c
b00000000000000000000000000001101 /"
17"
#740
07"
#750
b00000000000000000000000000010100 +
b0000000000001100 c
b00000000000000000000000000101000 /"
17"
#760
07"
#770
b00000000000000000000000000001010 +
b0000000000001101 c
b00000000000000000000000000010100 /"
17"
#780
07"
#790
b00000000000000000000000000000101 +
b0000000000001110 c
b00000000000000000000000000001010 /"
17"
#800
07"
#810
b00000000000000000000000000010000 +
b0000000000001111 c
b00000000000000000000000000000101 /"
17"
#820
07"
#830
b00000000000000000000000000001000 +
b0000000000010000 c
b00000000000000000000000000010000 /"
17"
#840
07"
#850
b00000000000000000000000000000100 +
b0000000000010001 c
b00000000000000000000000000001000 /"
17"
#860
07"
#870
b00000000000000000000000000000010 +
b0000000000010010 c
b00000000000000000000000000000100 /"
17"
#880
07"
#890
b00000000000000000000000000000001 +
b0000000000010011 c
b00000000000000000000000000000010 /"
17"
#900
07"
#910
b00000000000000000000000000000100 +
1C
b0000000000010100 c
b00000000000000000000000000000001 /"
17"
#920
07"
#930
b0010 3
1[
17"
#940
07"
#950
b0111 3
1;
b00000000000000000000000000001010 K
b0011 S
0[
b0000000000000001 c
b0000000000010100 m
17"
#960
07"
#970
b00000000000000000000000000000101 +
0;
0C
b00000000000000000000000000001010 /"
17"
#980
07"
#990
b00000000000000000000000000010000 +
b0000000000000010 c
b00000000000000000000000000000101 /"
17"
#1000
07"
#1010
b00000000000000000000000000001000 +
b0000000000000011 c
b00000000000000000000000000010000 /"
17"
#1020
07"
#1030
b00000000000000000000000000000100 +
b0000000000000100 c
b00000000000000000000000000001000 /"
17"
#1040
07"
#1050
b00000000000000000000000000000010 +
b0000000000000101 c
b00000000000000000000000000000100 /"
17"
#1060
07"
#1070
b00000000000000000000000000000001 +
b0000000000000110 c
b00000000000000000000000000000010 /"
17"
#1080
07"
#1090
b00000000000000000000000000000100 +
1C
b0000000000000111 c
b00000000000000000000000000000001 /"
17"
#1100
07"
#1110
b0011 3
1[
17"
#1120
07"
#1130
b0111 3
1;
b00000000000000000000000000001011 K
b0100 S
0[
b0000000000000001 c
b0000000000000111 n
17"
#1140
07"
#1150
b00000000000000000000000000100010 +
0;
0C
b00000000000000000000000000001011 /"
17"
#1160
07"
#1170
b00000000000000000000000000010001 +
b0000000000000010 c
b00000000000000000000000000100010 /"
17"
#1180
07"
#1190
b00000000000000000000000000110100 +
b0000000000000011 c
b00000000000000000000000000010001 /"
17"
#1200
07"
#1210
b00000000000000000000000000011010 +
b0000000000000100 c
b00000000000000000000000000110100 /"
17"
#1220
07"
#1230
b00000000000000000000000000001101 +
b0000000000000101 c
b00000000000000000000000000011010 /"
17"
#1240
07"
#1250
b00000000000000000000000000101000 +
b0000000000000110 c
b00000000000000000000000000001101 /"
17"
#1260
07"
#1270
b00000000000000000000000000010100 +
b0000000000000111 c
b00000000000000000000000000101000 /"
17"
#1280
07"
#1290
b00000000000000000000000000001010 +
b0000000000001000 c
b00000000000000000000000000010100 /"
17"
#1300
07"
#1310
b00000000000000000000000000000101 +
b0000000000001001 c
b00000000000000000000000000001010 /"
17"
#1320
07"
#1330
b00000000000000000000000000010000 +
b0000000000001010 c
b00000000000000000000000000000101 /"
17"
#1340
07"
#1350
b00000000000000000000000000001000 +
b0000000000001011 c
b00000000000000000000000000010000 /"
17"
#1360
07"
#1370
b00000000000000000000000000000100 +
b0000000000001100 c
b00000000000000000000000000001000 /"
17"
#1380
07"
#1390
b00000000000000000000000000000010 +
b0000000000001101 c
b00000000000000000000000000000100 /"
17"
#1400
07"
#1410
b00000000000000000000000000000001 +
b0000000000001110 c
b00000000000000000000000000000010 /"
17"
#1420
07"
#1430
b00000000000000000000000000000100 +
1C
b0000000000001111 c
b00000000000000000000000000000001 /"
17"
#1440
07"
#1450
b0100 3
1[
17"
#1460
07"
#1470
b0111 3
1;
b00000000000000000000000000001100 K
b0101 S
0[
b0000000000000001 c
b0000000000001111 o
17"
#1480
07"
#1490
b00000000000000000000000000000110 +
0;
0C
b00000000000000000000000000001100 /"
17"
#1500
07"
#1510
b00000000000000000000000000000011 +
b0000000000000010 c
b00000000000000000000000000000110 /"
17"
#1520
07"
#1530
b00000000000000000000000000001010 +
b0000000000000011 c
b00000000000000000000000000000011 /"
17"
#1540
07"
#1550
b00000000000000000000000000000101 +
b0000000000000100 c
b00000000000000000000000000001010 /"
17"
#1560
07"
#1570
b00000000000000000000000000010000 +
b0000000000000101 c
b00000000000000000000000000000101 /"
17"
#1580
07"
#1590
b00000000000000000000000000001000 +
b0000000000000110 c
b00000000000000000000000000010000 /"
17"
#1600
07"
#1610
b00000000000000000000000000000100 +
b0000000000000111 c
b00000000000000000000000000001000 /"
17"
#1620
07"
#1630
b00000000000000000000000000000010 +
b0000000000001000 c
b00000000000000000000000000000100 /"
17"
#1640
07"
#1650
b00000000000000000000000000000001 +
b0000000000001001 c
b00000000000000000000000000000010 /"
17"
#1660
07"
#1670
b00000000000000000000000000000100 +
1C
b0000000000001010 c
b00000000000000000000000000000001 /"
17"
#1680
07"
#1690
b0101 3
1[
17"
#1700
07"
#1710
b0111 3
1;
b00000000000000000000000000001101 K
b0110 S
0[
b0000000000000001 c
b0000000000001010 p
17"
#1720
07"
#1730
b00000000000000000000000000101000 +
0;
0C
b00000000000000000000000000001101 /"
17"
#1740
07"
#1750
b00000000000000000000000000010100 +
b0000000000000010 c
b00000000000000000000000000101000 /"
17"
#1760
07"
#1770
b00000000000000000000000000001010 +
b0000000000000011 c
b00000000000000000000000000010100 /"
17"
#1780
07"
#1790
b00000000000000000000000000000101 +
b0000000000000100 c
b00000000000000000000000000001010 /"
17"
#1800
07"
#1810
b00000000000000000000000000010000 +
b0000000000000101 c
b00000000000000000000000000000101 /"
17"
#1820
07"
#1830
b00000000000000000000000000001000 +
b0000000000000110 c
b00000000000000000000000000010000 /"
17"
#1840
07"
#1850
b00000000000000000000000000000100 +
b0000000000000111 c
b00000000000000000000000000001000 /"
17"
#1860
07"
#1870
b00000000000000000000000000000010 +
b0000000000001000 c
b00000000000000000000000000000100 /"
17"
#1880
07"
#1890
b00000000000000000000000000000001 +
b0000000000001001 c
b00000000000000000000000000000010 /"
17"
#1900
07"
#1910
b00000000000000000000000000000100 +
1C
b0000000000001010 c
b00000000000000000000000000000001 /"
17"
#1920
07"
#1930
b0110 3
1[
17"
#1940
07"
#1950
b0111 3
1;
b00000000000000000000000000001110 K
b0111 S
0[
b0000000000000001 c
b0000000000001010 q
17"
#1960
07"
#1970
b00000000000000000000000000000111 +
0;
0C
b00000000000000000000000000001110 /"
17"
#1980
07"
#1990
b00000000000000000000000000010110 +
b0000000000000010 c
b00000000000000000000000000000111 /"
17"
#2000
07"
#2010
b00000000000000000000000000001011 +
b0000000000000011 c
b00000000000000000000000000010110 /"
17"
#2020
07"
#2030
b00000000000000000000000000100010 +
b0000000000000100 c
b00000000000000000000000000001011 /"
17"
#2040
07"
#2050
b00000000000000000000000000010001 +
b0000000000000101 c
b00000000000000000000000000100010 /"
17"
#2060
07"
#2070
b00000000000000000000000000110100 +
b0000000000000110 c
b00000000000000000000000000010001 /"
17"
#2080
07"
#2090
b00000000000000000000000000011010 +
b0000000000000111 c
b00000000000000000000000000110100 /"
17"
#2100
07"
#2110
b00000000000000000000000000001101 +
b0000000000001000 c
b00000000000000000000000000011010 /"
17"
#2120
07"
#2130
b00000000000000000000000000101000 +
b0000000000001001 c
b00000000000000000000000000001101 /"
17"
#2140
07"
#2150
b00000000000000000000000000010100 +
b0000000000001010 c
b00000000000000000000000000101000 /"
17"
#2160
07"
#2170
b00000000000000000000000000001010 +
b0000000000001011 c
b00000000000000000000000000010100 /"
17"
#2180
07"
#2190
b00000000000000000000000000000101 +
b0000000000001100 c
b00000000000000000000000000001010 /"
17"
#2200
07"
#2210
b00000000000000000000000000010000 +
b0000000000001101 c
b00000000000000000000000000000101 /"
17"
#2220
07"
#2230
b00000000000000000000000000001000 +
b0000000000001110 c
b00000000000000000000000000010000 /"
17"
#2240
07"
#2250
b00000000000000000000000000000100 +
b0000000000001111 c
b00000000000000000000000000001000 /"
17"
#2260
07"
#2270
b00000000000000000000000000000010 +
b0000000000010000 c
b00000000000000000000000000000100 /"
17"
#2280
07"
#2290
b00000000000000000000000000000001 +
b0000000000010001 c
b00000000000000000000000000000010 /"
17"
#2300
07"
#2310
b00000000000000000000000000000100 +
1C
b0000000000010010 c
b00000000000000000000000000000001 /"
17"
#2320
07"
#2330
1[
17"
#2340
07"
#2350
1;
b00000000000000000000000000001111 K
b1000 S
0[
b0000000000000001 c
b0000000000010010 r
17"
#2360
07"
#2370
b00000000000000000000000000101110 +
0;
0C
b00000000000000000000000000001111 /"
17"
b0000000000010010 W"
#2380
07"
#2390
b00000000000000000000000000010111 +
b0000000000000010 c
b00000000000000000000000000101110 /"
17"
#2400
07"
#2410
b00000000000000000000000001000110 +
b0000000000000011 c
b00000000000000000000000000010111 /"
17"
#2420
07"
#2430
b00000000000000000000000000100011 +
b0000000000000100 c
b00000000000000000000000001000110 /"
17"
#2440
07"
#2450
b00000000000000000000000001101010 +
b0000000000000101 c
b00000000000000000000000000100011 /"
17"
#2460
07"
#2470
b00000000000000000000000000110101 +
b0000000000000110 c
b00000000000000000000000001101010 /"
17"
#2480
07"
#2490
b00000000000000000000000010100000 +
b0000000000000111 c
b00000000000000000000000000110101 /"
17"
#2500
07"
#2510
b00000000000000000000000001010000 +
b0000000000001000 c
b00000000000000000000000010100000 /"
17"
#2520
07"
#2530
b00000000000000000000000000101000 +
b0000000000001001 c
b00000000000000000000000001010000 /"
17"
#2540
07"
#2550
b00000000000000000000000000010100 +
b0000000000001010 c
b00000000000000000000000000101000 /"
17"
#2560
07"
#2570
b00000000000000000000000000001010 +
b0000000000001011 c
b00000000000000000000000000010100 /"
17"
#2580
07"
#2590
b00000000000000000000000000000101 +
b0000000000001100 c
b00000000000000000000000000001010 /"
17"
#2600
07"
#2610
b00000000000000000000000000010000 +
b0000000000001101 c
b00000000000000000000000000000101 /"
17"
#2620
07"
#2630
b00000000000000000000000000001000 +
b0000000000001110 c
b00000000000000000000000000010000 /"
17"
#2640
07"
#2650
b00000000000000000000000000000100 +
b0000000000001111 c
b00000000000000000000000000001000 /"
17"
#2660
07"
#2670
b00000000000000000000000000000010 +
b0000000000010000 c
b00000000000000000000000000000100 /"
17"
#2680
07"
#2690
b00000000000000000000000000000001 +
b0000000000010001 c
b00000000000000000000000000000010 /"
17"
#2700
07"
#2710
b00000000000000000000000000000100 +
1C
b0000000000010010 c
b00000000000000000000000000000001 /"
17"
#2720
07"
#2730
b1000 3
1[
17"
#2740
07"
#2750
b0111 3
1;
b00000000000000000000000000010000 K
b1001 S
0[
b0000000000000001 c
b0000000000010010 s
17"
b0000000000000000 W"
#2760
07"
#2770
b00000000000000000000000000001000 +
0;
0C
b00000000000000000000000000010000 /"
17"
b0000000000010010 W"
#2780
07"
#2790
b00000000000000000000000000000100 +
b0000000000000010 c
b00000000000000000000000000001000 /"
17"
#2800
07"
#2810
b00000000000000000000000000000010 +
b0000000000000011 c
b00000000000000000000000000000100 /"
17"
#2820
07"
#2830
b00000000000000000000000000000001 +
b0000000000000100 c
b00000000000000000000000000000010 /"
17"
#2840
07"
#2850
b00000000000000000000000000000100 +
1C
b0000000000000101 c
b00000000000000000000000000000001 /"
17"
#2860
07"
#2870
b1001 3
1[
17"
#2880
07"
#2890
b0111 3
1;
b00000000000000000000000000010001 K
b1010 S
0[
b0000000000000001 c
b0000000000000101 t
17"
b0000000000000000 W"
#2900
07"
#2910
b00000000000000000000000000110100 +
0;
0C
b00000000000000000000000000010001 /"
17"
b0000000000010010 W"
#2920
07"
#2930
b00000000000000000000000000011010 +
b0000000000000010 c
b00000000000000000000000000110100 /"
17"
#2940
07"
#2950
b00000000000000000000000000001101 +
b0000000000000011 c
b00000000000000000000000000011010 /"
17"
#2960
07"
#2970
b00000000000000000000000000101000 +
b0000000000000100 c
b00000000000000000000000000001101 /"
17"
#2980
07"
#2990
b00000000000000000000000000010100 +
b0000000000000101 c
b00000000000000000000000000101000 /"
17"
#3000
07"
#3010
b00000000000000000000000000001010 +
b0000000000000110 c
b00000000000000000000000000010100 /"
17"
#3020
07"
#3030
b00000000000000000000000000000101 +
b0000000000000111 c
b00000000000000000000000000001010 /"
17"
#3040
07"
#3050
b00000000000000000000000000010000 +
b0000000000001000 c
b00000000000000000000000000000101 /"
17"
#3060
07"
#3070
b00000000000000000000000000001000 +
b0000000000001001 c
b00000000000000000000000000010000 /"
17"
#3080
07"
#3090
b00000000000000000000000000000100 +
b0000000000001010 c
b00000000000000000000000000001000 /"
17"
#3100
07"
#3110
b00000000000000000000000000000010 +
b0000000000001011 c
b00000000000000000000000000000100 /"
17"
#3120
07"
#3130
b00000000000000000000000000000001 +
b0000000000001100 c
b00000000000000000000000000000010 /"
17"
#3140
07"
#3150
b00000000000000000000000000000100 +
1C
b0000000000001101 c
b00000000000000000000000000000001 /"
17"
#3160
07"
#3170
b1010 3
1[
17"
#3180
07"
#3190
b0111 3
1;
b00000000000000000000000000010010 K
b1011 S
0[
b0000000000000001 c
b0000000000001101 u
17"
b0000000000000000 W"
#3200
07"
#3210
b00000000000000000000000000001001 +
0;
0C
b00000000000000000000000000010010 /"
17"
b0000000000010010 W"
#3220
07"
#3230
b00000000000000000000000000011100 +
b0000000000000010 c
b00000000000000000000000000001001 /"
17"
#3240
07"
#3250
b00000000000000000000000000001110 +
b0000000000000011 c
b00000000000000000000000000011100 /"
17"
#3260
07"
#3270
b00000000000000000000000000000111 +
b0000000000000100 c
b00000000000000000000000000001110 /"
17"
#3280
07"
#3290
b00000000000000000000000000010110 +
b0000000000000101 c
b00000000000000000000000000000111 /"
17"
#3300
07"
#3310
b00000000000000000000000000001011 +
b0000000000000110 c
b00000000000000000000000000010110 /"
17"
#3320
07"
#3330
b00000000000000000000000000100010 +
b0000000000000111 c
b00000000000000000000000000001011 /"
17"
#3340
07"
#3350
b00000000000000000000000000010001 +
b0000000000001000 c
b00000000000000000000000000100010 /"
17"
#3360
07"
#3370
b00000000000000000000000000110100 +
b0000000000001001 c
b00000000000000000000000000010001 /"
17"
#3380
07"
#3390
b00000000000000000000000000011010 +
b0000000000001010 c
b00000000000000000000000000110100 /"
17"
#3400
07"
#3410
b00000000000000000000000000001101 +
b0000000000001011 c
b00000000000000000000000000011010 /"
17"
#3420
07"
#3430
b00000000000000000000000000101000 +
b0000000000001100 c
b00000000000000000000000000001101 /"
17"
#3440
07"
#3450
b00000000000000000000000000010100 +
b0000000000001101 c
b00000000000000000000000000101000 /"
17"
#3460
07"
#3470
b00000000000000000000000000001010 +
b0000000000001110 c
b00000000000000000000000000010100 /"
17"
#3480
07"
#3490
b00000000000000000000000000000101 +
b0000000000001111 c
b00000000000000000000000000001010 /"
17"
#3500
07"
#3510
b00000000000000000000000000010000 +
b0000000000010000 c
b00000000000000000000000000000101 /"
17"
#3520
07"
#3530
b00000000000000000000000000001000 +
b0000000000010001 c
b00000000000000000000000000010000 /"
17"
#3540
07"
#3550
b00000000000000000000000000000100 +
b0000000000010010 c
b00000000000000000000000000001000 /"
17"
#3560
07"
#3570
b00000000000000000000000000000010 +
b0000000000010011 c
b00000000000000000000000000000100 /"
17"
#3580
07"
#3590
b00000000000000000000000000000001 +
b0000000000010100 c
b00000000000000000000000000000010 /"
17"
#3600
07"
#3610
b00000000000000000000000000000100 +
1C
b0000000000010101 c
b00000000000000000000000000000001 /"
17"
#3620
07"
#3630
b1011 3
1[
17"
#3640
07"
#3650
b0111 3
1;
b00000000000000000000000000010011 K
b1100 S
0[
b0000000000000001 c
b0000000000010101 v
17"
b0000000000000000 W"
#3660
07"
#3670
b00000000000000000000000000111010 +
0;
0C
b00000000000000000000000000010011 /"
17"
b0000000000010010 W"
#3680
07"
#3690
b00000000000000000000000000011101 +
b0000000000000010 c
b00000000000000000000000000111010 /"
17"
#3700
07"
#3710
b00000000000000000000000001011000 +
b0000000000000011 c
b00000000000000000000000000011101 /"
17"
#3720
07"
#3730
b00000000000000000000000000101100 +
b0000000000000100 c
b00000000000000000000000001011000 /"
17"
#3740
07"
#3750
b00000000000000000000000000010110 +
b0000000000000101 c
b00000000000000000000000000101100 /"
17"
#3760
07"
#3770
b00000000000000000000000000001011 +
b0000000000000110 c
b00000000000000000000000000010110 /"
17"
#3780
07"
#3790
b00000000000000000000000000100010 +
b0000000000000111 c
b00000000000000000000000000001011 /"
17"
#3800
07"
#3810
b00000000000000000000000000010001 +
b0000000000001000 c
b00000000000000000000000000100010 /"
17"
#3820
07"
#3830
b00000000000000000000000000110100 +
b0000000000001001 c
b00000000000000000000000000010001 /"
17"
#3840
07"
#3850
b00000000000000000000000000011010 +
b0000000000001010 c
b00000000000000000000000000110100 /"
17"
#3860
07"
#3870
b00000000000000000000000000001101 +
b0000000000001011 c
b00000000000000000000000000011010 /"
17"
#3880
07"
#3890
b00000000000000000000000000101000 +
b0000000000001100 c
b00000000000000000000000000001101 /"
17"
#3900
07"
#3910
b00000000000000000000000000010100 +
b0000000000001101 c
b00000000000000000000000000101000 /"
17"
#3920
07"
#3930
b00000000000000000000000000001010 +
b0000000000001110 c
b00000000000000000000000000010100 /"
17"
#3940
07"
#3950
b00000000000000000000000000000101 +
b0000000000001111 c
b00000000000000000000000000001010 /"
17"
#3960
07"
#3970
b00000000000000000000000000010000 +
b0000000000010000 c
b00000000000000000000000000000101 /"
17"
#3980
07"
#3990
b00000000000000000000000000001000 +
b0000000000010001 c
b00000000000000000000000000010000 /"
17"
#4000
07"
#4010
b00000000000000000000000000000100 +
b0000000000010010 c
b00000000000000000000000000001000 /"
17"
#4020
07"
#4030
b00000000000000000000000000000010 +
b0000000000010011 c
b00000000000000000000000000000100 /"
17"
#4040
07"
#4050
b00000000000000000000000000000001 +
b0000000000010100 c
b00000000000000000000000000000010 /"
17"
#4060
07"
#4070
b00000000000000000000000000000100 +
1C
b0000000000010101 c
b00000000000000000000000000000001 /"
17"
#4080
07"
#4090
b1100 3
1[
17"
#4100
07"
#4110
b0111 3
1;
b00000000000000000000000000010100 K
b1101 S
0[
b0000000000000001 c
b0000000000010101 w
17"
b0000000000000000 W"
#4120
07"
#4130
b00000000000000000000000000001010 +
0;
0C
b00000000000000000000000000010100 /"
17"
b0000000000010010 W"
#4140
07"
#4150
b00000000000000000000000000000101 +
b0000000000000010 c
b00000000000000000000000000001010 /"
17"
#4160
07"
#4170
b00000000000000000000000000010000 +
b0000000000000011 c
b00000000000000000000000000000101 /"
17"
#4180
07"
#4190
b00000000000000000000000000001000 +
b0000000000000100 c
b00000000000000000000000000010000 /"
17"
#4200
07"
#4210
b00000000000000000000000000000100 +
b0000000000000101 c
b00000000000000000000000000001000 /"
17"
#4220
07"
#4230
b00000000000000000000000000000010 +
b0000000000000110 c
b00000000000000000000000000000100 /"
17"
#4240
07"
#4250
b00000000000000000000000000000001 +
b0000000000000111 c
b00000000000000000000000000000010 /"
17"
#4260
07"
#4270
b00000000000000000000000000000100 +
1C
b0000000000001000 c
b00000000000000000000000000000001 /"
17"
#4280
07"
#4290
b1101 3
1[
17"
#4300
07"
#4310
b0111 3
1;
b00000000000000000000000000010101 K
b1110 S
0[
b0000000000000001 c
b0000000000001000 x
17"
b0000000000000000 W"
#4320
07"
#4330
b00000000000000000000000001000000 +
0;
0C
b00000000000000000000000000010101 /"
17"
b0000000000010010 W"
#4340
07"
#4350
b00000000000000000000000000100000 +
b0000000000000010 c
b00000000000000000000000001000000 /"
17"
#4360
07"
#4370
b00000000000000000000000000010000 +
b0000000000000011 c
b00000000000000000000000000100000 /"
17"
#4380
07"
#4390
b00000000000000000000000000001000 +
b0000000000000100 c
b00000000000000000000000000010000 /"
17"
#4400
07"
#4410
b00000000000000000000000000000100 +
b0000000000000101 c
b00000000000000000000000000001000 /"
17"
#4420
07"
#4430
b00000000000000000000000000000010 +
b0000000000000110 c
b00000000000000000000000000000100 /"
17"
#4440
07"
#4450
b00000000000000000000000000000001 +
b0000000000000111 c
b00000000000000000000000000000010 /"
17"
#4460
07"
#4470
b00000000000000000000000000000100 +
1C
b0000000000001000 c
b00000000000000000000000000000001 /"
17"
#4480
07"
#4490
b1110 3
1[
17"
#4500
07"
#4510
b0111 3
1;
b00000000000000000000000000010110 K
b1111 S
0[
b0000000000000001 c
b0000000000001000 y
17"
b0000000000000000 W"
#4520
07"
#4530
b00000000000000000000000000001011 +
0;
0C
b00000000000000000000000000010110 /"
17"
b0000000000010010 W"
#4540
07"
#4550
b00000000000000000000000000100010 +
b0000000000000010 c
b00000000000000000000000000001011 /"
17"
#4560
07"
#4570
b00000000000000000000000000010001 +
b0000000000000011 c
b00000000000000000000000000100010 /"
17"
#4580
07"
#4590
b00000000000000000000000000110100 +
b0000000000000100 c
b00000000000000000000000000010001 /"
17"
